Workbook

Sheet Proposta Comercial
I5: PROPOSTA N° PB0121S052T
B10: Campina Grande - PB, 05 de fevereiro de 2021.
B18: Temos a satisfação de apresentar a Vossa Senhoria e para vossa análise, nossa proposta técnica comercial para a aquisição e instalação de um Sistema Solar fotovoltaico conectado à rede de distribuição da concessionária de energia. Nosso compromisso é de fornecer equipamentos certificados pelo INMETRO, promover a sustentabilidade colaborando com a redução de emissão de CO2 e de agregar valor ao vosso imóvel.
B64: NOME/RAZÃO SOCIAL: | D64: PORTA DO MAR E HZALHO | H64: CPF/CNPJ: | J64: 12.940.821/0001-97
B66: LOGRADOURO: | D66: RUA CARDOSO VIEIRA | H66: BAIRRO: | J66: CENTRO
B68: CIDADE: | C68: CAMPINA GRANDE | G68: UF: | H68: PB | I68: CEP: | J68: 58400-097
B70: FONE: | C70: (83) 3331-2117 | E70: E-MAIL: | F70: hzalho@hotmail.com | I70: COORD.: | J70: -7.217802 | K70: -35.886420
B75: CONCESSIONÁRIA: | D75: ENERGISA BORBOREMA | G75: N° DA UNIDADE: | I75: 4/116435-9
B77: FORNECIMENTO: | D77: TRIFÁSICO | F77: CONSUMO MÉDIO ANUAL (kWh): | I77: 1500 | J77: TARIFA: | K77: 0.72
B79: PRODUÇÃO DESEJADA (kWh): | E79: =$I$77 -> 1500 | F79: CLASSE DE ATENDIMENTO: | I79: COMERCIAL
B83: DIMENSIONAMENTO CONFORME DADOS DO SWERA/NASA/INPE | H83: POTÊNCIA TOTAL EM kWp: | K83: =($D$91*$D$93)/1000 -> 11.34
B85: MÓDULOS / PAINEIS | E85: INVERSOR(ES) | I85: ESTRUTURAS
B87: MARCA: | C87: RENO | E87: MARCA: | F87: RENO | I87: MARCA: | J87: ART SIGN
B89: MODELO: | C89: RENO-405P | E89: MODELO: | F89: RENO 10k PLUS | I89: MODELO: | J89: FIBROCIMENTO
B91: POTÊNCIA EM (W): | D91: 405 | E91: POTÊNCIA EM kW: | G91: 10 | I91: QUANTIDADE: | K91: =$D$93 -> 28
B93: QUANTIDADE: | D93: 28 | E93: QUANTIDADE: | G93: 1 | I93: STRINGBOX CC: | K93: 2/2
B95: GARANTIA EM ANOS: | D95: 12 | E95: GARANTIA EM ANOS: | G95: 6 | I95: STRINGBOX CA: | K95: 1
C97: ="*"&$D$95&" anos para defeitos de fabricação e 25 anos de garantia de performance linear de geração." -> *12 anos para defeitos de fabricação e 25 anos de garantia de performance linear de geração.
C98: Todos os equipamentos possuem certificação e registro no INMETRO.
B108: CUSTO TOTAL DO INVESTIMENTO | H108: VALOR INVESTIDO: | J108: 59000
B115: * Prazo para a instalação do sistema: até 15 dias após a chegada do equipamento.
B117: ** Valor destinado a elaboração do projeto elétrico, elaboração do Parecer de Acesso junto à Concessionária e serviço de instalação do sistema fotovoltaico.
B120: ANÁLISE DA VIABILIDADE FINANCEIRA | H120: SUSTENTABILIDADE
B122: ESTIMATIVA DE GERAÇÃO MENSAL EM (kWh) NO 1° ANO: | G122: =MEDIAN(Dados!D12:O12) -> 666.9 | I122: =" "&Dados!$B$43&" toneladas de CO2 não emitidas na atmosfera" -> 132,75 toneladas de CO2 não emitidas na atmosfera
B124: ESTIMATIVA DE GERAÇÃO ANUAL EM (kWh) NO 1° ANO: | G124: =Dados!$P$12 -> 8226.8222
B126: ESTIMATIVA DE ECONOMIA ANUAL NO 1° ANO: | F126: =$G$124*$K$77 -> 5923.312
B128: ESTIMATIVA DE ECONOMIA EM 25 ANOS: | F128: =Dados!$P$40 -> 243161.86 | I128: ="o equivalente a plantar "&Dados!$B$41&" árvores ao longo dos 25 anos" -> o equivalente a plantar 947,835 árvores ao longo dos 25 anos
B130: TIR | D130: =IRR(Dados!N15:O40) -> 0.25669251 | E130: TMA | G130: 0.2
B132: PAYBACK EM ANOS: | F132: =Dados!S19 -> 4.3203908
B135: ______________________________________ | G135: ______________________________________
B136: =$D$64 -> PORTA DO MAR E HZALHO | G136: SOLVE ENERGY - Soluções Energéticas
B137: ="CPF/CNPJ: "&$J$64&"" -> CPF/CNPJ: 12.940.821/0001-97 | G137: CNPJ: 40.123.832/0001-10

Sheet Dados
A1: POT. INVERSOR | B1: 5 | C1: kW | D1: POTÊNCIA DOS MÓDULOS | G1: 450 | H1: QUANTIDADE | J1: 13 | K1: POTÊNCIA DO SISTEMA | N1: =(G1*J1)/1000 -> 5.85 | O1: kWp
A2: QTDE INVERSOR | B2: 1
D3: CONSUMO MENSAL EM kWh
A4: UF | B4: ATENDIMENTO | D4: JAN | E4: FEV | F4: MAR | G4: ABR | H4: MAI | I4: JUN | J4: JUL | K4: AGO | L4: SET | M4: OUT | N4: NOV | O4: DEZ | P4: MÉDIA
A5: AC | B5: RESIDENCIAL | D5: 700 | E5: 700 | F5: 700 | G5: 700 | H5: 700 | I5: 700 | J5: 700 | K5: 700 | L5: 700 | M5: 700 | N5: 700 | O5: 700 | P5: =(SUM(D4:O5)/12) -> 700
A6: AL | B6: COMERCIAL | D6: IRRADIAÇÃO MÉDIA GLOBAL ANUAL EM (kWh/m²/dia) | Q6: %
A7: BA | B7: INDUSTRIAL | D7: JAN | E7: FEV | F7: MAR | G7: ABR | H7: MAI | I7: JUN | J7: JUL | K7: AGO | L7: SET | M7: OUT | N7: NOV | O7: DEZ | P7: MÉDIA | Q7: 0.2
A8: CE | B8: PODER PÚBLICO | D8: 4.59 | E8: 4.71 | F8: 4.9456 | G8: 4.79 | H8: 4.42 | I8: 4.59 | J8: 4.69 | K8: 5.14 | L8: 5.52 | M8: 5.43 | N8: 5.11 | O8: 4.66 | P8: =MEDIAN(D8:O8) -> 4.75
A9: MA | B9: RURAL | D9: =D8-(D8*$Q$7) -> 3.672 | E9: =E8-(E8*$Q$7) -> 3.768 | F9: =F8-(F8*$Q$7) -> 3.95648 | G9: =G8-(G8*$Q$7) -> 3.832 | H9: =H8-(H8*$Q$7) -> 3.536 | I9: =I8-(I8*$Q$7) -> 3.672 | J9: =J8-(J8*$Q$7) -> 3.752 | K9: =K8-(K8*$Q$7) -> 4.112 | ... O9: =O8-(O8*$Q$7) -> 3.728 | P9: =MEDIAN(D9:O9) -> 3.8
A10: PB | B10: SERVIÇO PÚBLICO | D10: ESTIMATIVA DE GERAÇÃO MÉDIA MENSAL EM kWh
A11: PE | D11: JAN | E11: FEV | F11: MAR | G11: ABR | H11: MAI | I11: JUN | J11: JUL | K11: AGO | L11: SET | M11: OUT | N11: NOV | O11: DEZ | P11: SOMA
A12: PI | D12: =((($G$1*$J$1)*D9)*30)/1000 -> 644.436 | E12: =((($G$1*$J$1)*E9)*30)/1000 -> 661.284 | F12: =((($G$1*$J$1)*F9)*30)/1000 -> 694.36224 | G12: =((($G$1*$J$1)*G9)*30)/1000 -> 672.516 | H12: =((($G$1*$J$1)*H9)*30)/1000 -> 620.568 | I12: =((($G$1*$J$1)*I9)*30)/1000 -> 644.436 | J12: =((($G$1*$J$1)*J9)*30)/1000 -> 658.476 | K12: =((($G$1*$J$1)*K9)*30)/1000 -> 721.656 | ... O12: =((($G$1*$J$1)*O9)*30)/1000 -> 654.264 | P12: =SUM(D12:O12) -> 8226.8222 | Q12: =(SUM(D12:O12)/12) -> 685.56852
A13: RN | D13: ESTIMATIVA DE RETORNO FINANCEIRO | Q13: 0.05
A14: SE | B14: CAPEX em R$ | D14: ANO | E14: % | F14: kWh | G14: R$ | H14: REEMBOLSO | J14: CAPEX | L14: OPEX | N14: ANUAL | P14: ACUMULADO
B15: =((B23*45%)+B23) -> 29058.826 | C15: =$Q$12 -> 685.56852 | D15: 0 | E15: - | F15: - | G15: 0.76 | H15: - | J15: =-($B$15) -> -29058.826 | L15: - | N15: =J15 -> -29058.826 | P15: =N15 -> -29058.826
A16: FORNECIMENTO | C16: =$C$15*E16 -> 668.42931 | D16: 1 | E16: 0.975 | F16: =($P$12*E16) -> 8021.1517 | G16: =G15+(G15*$Q$13) -> 0.798 | H16: =F16*G16 -> 6400.879 | J16: 0 | L16: =-(12*$J$1) -> -156 | N16: =SUM(H16:M16) -> 6244.879 | P16: =P15+N16 -> -22813.947
A17: MONOFÁSICO | C17: =$C$15*E17 -> 665.00146 | D17: 2 | E17: 0.97 | F17: =($P$12*E17) -> 7980.0176 | G17: =G16+(G16*$Q$13) -> 0.8379 | H17: =F17*G17 -> 6686.4567 | J17: 0 | L17: =(L16*$Q$13)+L16 -> -163.8 | N17: =SUM(H17:M17) -> 6522.6567 | P17: =P16+N17 -> -16291.291
A18: BIFÁSICO | C18: =$C$15*E18 -> 660.88805 | D18: 3 | E18: 0.964 | F18: =($P$12*E18) -> 7930.6566 | G18: =G17+(G17*$Q$13) -> 0.879795 | H18: =F18*G18 -> 6977.3521 | J18: 0 | L18: =(L17*$Q$13)+L17 -> -171.99 | N18: =SUM(H18:M18) -> 6805.3621 | P18: =P17+N18 -> -9485.9287 | S18: payback
A19: TRIFÁSICO | C19: =$C$15*E19 -> 657.46021 | D19: 4 | E19: 0.959 | F19: =($P$12*E19) -> 7889.5225 | G19: =G18+(G18*$Q$13) -> 0.92378475 | H19: =F19*G19 -> 7288.2206 | J19: 0 | L19: =(L18*$Q$13)+L18 -> -180.5895 | N19: =SUM(H19:M19) -> 7107.6311 | P19: =P18+N19 -> -2378.2976 | S19: =(P19*-1)/N20+D19 -> 4.3203908
C20: =$C$15*E20 -> 654.03237 | D20: 5 | E20: 0.954 | F20: =($P$12*E20) -> 7848.3884 | G20: =G19+(G19*$Q$13) -> 0.96997399 | H20: =F20*G20 -> 7612.7326 | J20: 0 | L20: =(L19*$Q$13)+L19 -> -189.61898 | N20: =SUM(H20:M20) -> 7423.1136 | P20: =P19+N20 -> 5044.8161
C21: =$C$15*E21 -> 649.91896 | D21: 6 | E21: 0.948 | F21: =($P$12*E21) -> 7799.0275 | G21: =G20+(G20*$Q$13) -> 1.0184727 | H21: =F21*G21 -> 7943.0965 | J21: 0 | L21: =(L20*$Q$13)+L20 -> -199.09992 | N21: =SUM(H21:M21) -> 7743.9966 | P21: =P20+N21 -> 12788.813
C22: =$C$15*E22 -> 646.49111 | D22: 7 | E22: 0.943 | F22: =($P$12*E22) -> 7757.8934 | G22: =G21+(G21*$Q$13) -> 1.0693963 | H22: =F22*G22 -> 8296.2626 | J22: 0 | L22: =(L21*$Q$13)+L21 -> -209.05492 | N22: =SUM(H22:M22) -> 8087.2077 | P22: =P21+N22 -> 20876.02
A23: PREÇO COMPRA | B23: 20040.57 | C23: =$C$15*E23 -> 643.06327 | D23: 8 | E23: 0.938 | F23: =($P$12*E23) -> 7716.7593 | G23: =G22+(G22*$Q$13) -> 1.1228661 | H23: =F23*G23 -> 8664.8877 | J23: 0 | L23: =(L22*$Q$13)+L22 -> -219.50767 | N23: =SUM(H23:M23) -> 8445.38 | P23: =P22+N23 -> 29321.4
A24: PROJETO 2% | B24: =B15*2% -> 581.17653 | C24: =$C$15*E24 -> 638.94986 | D24: 9 | E24: 0.932 | F24: =($P$12*E24) -> 7667.3983 | G24: =G23+(G23*$Q$13) -> 1.1790094 | H24: =F24*G24 -> 9039.935 | J24: 0 | L24: =(L23*$Q$13)+L23 -> -230.48305 | N24: =SUM(H24:M24) -> 8809.452 | P24: =P23+N24 -> 38130.852
A25: VENDA 5% | B25: =B15*5% -> 1452.9413 | C25: =$C$15*E25 -> 635.52202 | D25: 10 | E25: 0.927 | F25: =($P$12*E25) -> 7626.2642 | G25: =G24+(G24*$Q$13) -> 1.2379599 | H25: =F25*G25 -> 9441.0094 | J25: 0 | L25: =(L24*$Q$13)+L24 -> -242.0072 | N25: =SUM(H25:M25) -> 9199.0022 | P25: =P24+N25 -> 47329.855
A26: INSTALAÇÃO | B26: =J1*60 -> 780 | C26: =$C$15*E26 -> 631.40861 | D26: 11 | E26: 0.921 | F26: =($P$12*E26) -> 7576.9033 | G26: =G25+(G25*$Q$13) -> 1.2998579 | H26: =F26*G26 -> 9848.8977 | J26: 0 | L26: =(L25*$Q$13)+L25 -> -254.10756 | N26: =SUM(H26:M26) -> 9594.7901 | P26: =P25+N26 -> 56924.645
A27: TRANSPORTE 3% | B27: =B15*3% -> 871.76479 | C27: =$C$15*E27 -> 627.98076 | D27: 12 | E27: 0.916 | F27: =($P$12*E27) -> 7535.7692 | G27: =G26+(G26*$Q$13) -> 1.3648508 | H27: =F27*G27 -> 10285.201 | J27: 0 | L27: =(L26*$Q$13)+L26 -> -266.81294 | N27: =SUM(H27:M27) -> 10018.388 | P27: =P26+N27 -> 66943.032
A28: IMPOSTO 6% | B28: =(B15-B23)*6% -> 541.09539 | C28: =$C$15*E28 -> 624.55292 | D28: 13 | E28: 0.911 | F28: =($P$12*E28) -> 7494.6351 | G28: =G27+(G27*$Q$13) -> 1.4330933 | H28: =F28*G28 -> 10740.512 | J28: 0 | L28: =(L27*$Q$13)+L27 -> -280.15359 | N28: =SUM(H28:M28) -> 10460.358 | P28: =P27+N28 -> 77403.39
A29: ADM 2% | B29: =B15*2% -> 581.17653 | C29: =$C$15*E29 -> 620.43951 | D29: 14 | E29: 0.905 | F29: =($P$12*E29) -> 7445.2741 | G29: =G28+(G28*$Q$13) -> 1.504748 | H29: =F29*G29 -> 11203.261 | J29: 0 | L29: =(L28*$Q$13)+L28 -> -294.16127 | N29: =SUM(H29:M29) -> 10909.1 | P29: =P28+N29 -> 88312.491
A30: LUCRO | B30: =$B$15*$A$31 -> 3777.6474 | C30: =$C$15*E30 -> 617.01167 | D30: 15 | E30: 0.9 | F30: =($P$12*E30) -> 7404.14 | G30: =G29+(G29*$Q$13) -> 1.5799854 | H30: =F30*G30 -> 11698.433 | J30: 0 | L30: =(L29*$Q$13)+L29 -> -308.86933 | N30: =SUM(H30:M30) -> 11389.564 | P30: =P29+N30 -> 99702.055
A31: 0.13 | C31: =$C$15*E31 -> 612.21269 | D31: 16 | E31: 0.893 | F31: =($P$12*E31) -> 7346.5523 | G31: =G30+(G30*$Q$13) -> 1.6589847 | H31: =F31*G31 -> 12187.818 | J31: 0 | L31: =(L30*$Q$13)+L30 -> -324.3128 | N31: =SUM(H31:M31) -> 11863.505 | P31: =P30+N31 -> 111565.56
B32: =SUM(B23:B30) -> 28626.372 | C32: =$C$15*E32 -> 607.41371 | D32: 17 | E32: 0.886 | F32: =($P$12*E32) -> 7288.9645 | G32: =G31+(G31*$Q$13) -> 1.7419339 | H32: =F32*G32 -> 12696.895 | J32: 0 | L32: =(L31*$Q$13)+L31 -> -340.52844 | N32: =SUM(H32:M32) -> 12356.366 | P32: =P31+N32 -> 123921.93
C33: =$C$15*E33 -> 602.61473 | D33: 18 | E33: 0.879 | F33: =($P$12*E33) -> 7231.3767 | G33: =G32+(G32*$Q$13) -> 1.8290306 | H33: =F33*G33 -> 13226.409 | J33: 0 | L33: =(L32*$Q$13)+L32 -> -357.55486 | N33: =SUM(H33:M33) -> 12868.855 | P33: =P32+N33 -> 136790.78
C34: =$C$15*E34 -> 597.81575 | D34: 19 | E34: 0.872 | F34: =($P$12*E34) -> 7173.789 | G34: =G33+(G33*$Q$13) -> 1.9204821 | H34: =F34*G34 -> 13777.134 | J34: 0 | L34: =(L33*$Q$13)+L33 -> -375.4326 | N34: =SUM(H34:M34) -> 13401.701 | P34: =P33+N34 -> 150192.48
C35: =$C$15*E35 -> 593.70234 | D35: 20 | E35: 0.866 | F35: =($P$12*E35) -> 7124.4281 | G35: =G34+(G34*$Q$13) -> 2.0165063 | H35: =F35*G35 -> 14366.454 | J35: 0 | L35: =(L34*$Q$13)+L34 -> -394.20423 | N35: =SUM(H35:M35) -> 13972.25 | P35: =P34+N35 -> 164164.73
A36: CO2 | B36: ÁRVORES | C36: =$C$15*E36 -> 588.90336 | D36: 21 | E36: 0.859 | F36: =($P$12*E36) -> 7066.8403 | G36: =G35+(G35*$Q$13) -> 2.1173316 | H36: =F36*G36 -> 14962.844 | J36: 0 | L36: =(L35*$Q$13)+L35 -> -413.91444 | N36: =SUM(H36:M36) -> 14548.93 | P36: =P35+N36 -> 178713.66
A37: 1 ton | B37: 7.14 | C37: =$C$15*E37 -> 584.78995 | D37: 22 | E37: 0.853 | F37: =($P$12*E37) -> 7017.4794 | G37: =G36+(G36*$Q$13) -> 2.2231981 | H37: =F37*G37 -> 15601.247 | J37: 0 | L37: =(L36*$Q$13)+L36 -> -434.61016 | N37: =SUM(H37:M37) -> 15166.637 | P37: =P36+N37 -> 193880.3
A38: CONSUMO kWh | B38: EMISSÃO CO2 | C38: =$C$15*E38 -> 579.3054 | D38: 23 | E38: 0.845 | F38: =($P$12*E38) -> 6951.6648 | G38: =G37+(G37*$Q$13) -> 2.3343581 | H38: =F38*G38 -> 16227.675 | J38: 0 | L38: =(L37*$Q$13)+L37 -> -456.34067 | N38: =SUM(H38:M38) -> 15771.334 | P38: =P37+N38 -> 209651.63
A39: ='Proposta Comercial'!$I$77 -> 1500 | B39: =$A$39*0.295 -> 442.5 | C39: =$C$15*E39 -> 574.50642 | D39: 24 | E39: 0.838 | F39: =($P$12*E39) -> 6894.077 | G39: =G38+(G38*$Q$13) -> 2.451076 | H39: =F39*G39 -> 16897.906 | J39: 0 | L39: =(L38*$Q$13)+L38 -> -479.15771 | N39: =SUM(H39:M39) -> 16418.749 | P39: =P38+N39 -> 226070.38
A40: QTDE DE ÁRVORES EM: | C40: =$C$15*E40 -> 569.70744 | D40: 25 | E40: 0.831 | F40: =($P$12*E40) -> 6836.4893 | G40: =G39+(G39*$Q$13) -> 2.5736298 | H40: =F40*G40 -> 17594.592 | J40: 0 | L40: =(L39*$Q$13)+L39 -> -503.11559 | N40: =SUM(H40:M40) -> 17091.477 | P40: =P39+N40 -> 243161.86
A41: 25 ANOS | B41: =(((B39*12*25)/1000)*$B$37) -> 947.835
A42: TONELADAS DE CO2 | M42: TIR | N42: =IRR(N15:O40) -> 0.25669251
A43: 25 ANOS | B43: =(25*12*$B$39)/1000 -> 132.75 | M43: TMA | N43: 0.2
M44: VPL | N44: =NPV($N$43,$N$16:$O$40)+$N$15 -> 9693.8077
E64: 5546 | F64: 5669 | G64: 5767 | H64: 5231 | I64: 4626 | J64: 4063 | K64: 4164 | L64: 4898 | M64: 5491 | N64: 5751 | O64: 5994 | P64: 5764 | Q64: 5247
B90: 0 | C90: 1 | D90: 2 | E90: 3 | F90: 4 | G90: 5 | H90: 6 | I90: 7 | J90: 8 | K90: 9 | L90: 10 | M90: 11 | N90: 12 | O90: 13 | P90: 14 | Q90: 15 | R90: 16 | S90: 17 | T90: 18 | U90: 19 | V90: 20 | W90: 21 | X90: 22 | Y90: 23 | Z90: 24 | AA90: 25
B91: =P15 -> -29058.826 | C91: =P16 -> -22813.947 | D91: =P17 -> -16291.291 | E91: =P18 -> -9485.9287 | F91: =P19 -> -2378.2976
G92: =P20 -> 5044.8161 | H92: =P21 -> 12788.813 | I92: =P22 -> 20876.02 | J92: =P23 -> 29321.4 | K92: =P24 -> 38130.852 | L92: =P25 -> 47329.855 | M92: =P26 -> 56924.645 | N92: =P27 -> 66943.032 | O92: =P28 -> 77403.39 | P92: =P29 -> 88312.491 | Q92: =P30 -> 99702.055 | R92: =P31 -> 111565.56 | S92: =P32 -> 123921.93 | T92: =P33 -> 136790.78 | U92: =P34 -> 150192.48 | V92: =P35 -> 164164.73 | W92: =P36 -> 178713.66 | X92: =P37 -> 193880.3 | Y92: =P38 -> 209651.63 | Z92: =P39 -> 226070.38 | AA92: =P40 -> 243161.86

Sheet Planilha1
A2: LONGITUDE | B2: LATITUDE | C2: CIDADE | D2: ESTADO | E2: JAN | F2: FEV | G2: MAR | H2: ABR | I2: MAI | J2: JUN | K2: JUL | L2: AGO | M2: SET | N2: OUT | O2: NOV | P2: DEZ | Q2: MÉDIA
A3: -370093 | B3: -81528 | C3: São Sebastião do Umbuzeiro | D3: PB | E3: 6195 | F3: 5983 | G3: 6043 | H3: 5514 | I3: 4741 | J3: 4274 | K3: 4384 | L3: 5217 | M3: 6142 | N3: 6392 | O3: 6683 | P3: 6397 | Q3: 5664
A4: -370993 | B4: -8076 | C4: Zabelê | D4: PB | E4: 6187 | F4: 6042 | G4: 5992 | H4: 5513 | I4: 4737 | J4: 4314 | K4: 4463 | L4: 5219 | M4: 6166 | N4: 6425 | O4: 6725 | P4: 6447 | Q4: 5686
A5: -368554 | B5: -80778 | C5: São João do Tigre | D5: PB | E5: 6134 | F5: 5973 | G5: 5991 | H5: 5585 | I5: 4713 | J5: 4254 | K5: 4437 | L5: 5285 | M5: 6129 | N5: 6338 | O5: 6675 | P5: 6426 | Q5: 5662
A6: -371221 | B6: -78947 | C6: Monteiro | D6: PB | E6: 6300 | F6: 6131 | G6: 6152 | H6: 5702 | I6: 4902 | J6: 4399 | K6: 4556 | L6: 5314 | M6: 6284 | N6: 6508 | O6: 6775 | P6: 6426 | Q6: 5788
A7: -368245 | B7: -78855 | C7: Camalaú | D7: PB | E7: 6200 | F7: 6104 | G7: 6097 | H7: 5673 | I7: 4849 | J7: 4395 | K7: 4499 | L7: 5273 | M7: 6168 | N7: 6430 | O7: 6653 | P7: 6390 | Q7: 5728
A8: -366584 | B8: -77912 | C8: Congo | D8: PB | E8: 6137 | F8: 6012 | G8: 6053 | H8: 5631 | I8: 4838 | J8: 4359 | K8: 4479 | L8: 5212 | M8: 6028 | N8: 6325 | O8: 6535 | P8: 6274 | Q8: 5657
A9: -363166 | B9: -77527 | C9: Barra de São Miguel | D9: PB | E9: 6003 | F9: 5906 | G9: 5926 | H9: 5460 | I9: 4788 | J9: 4321 | K9: 4457 | L9: 5170 | M9: 5855 | N9: 6122 | O9: 6350 | P9: 6091 | Q9: 5538
A10: -381003 | B10: -77431 | C10: São José de Princesa | D10: PB | E10: 6157 | F10: 6109 | G10: 6139 | H10: 5720 | I10: 5048 | J10: 4690 | K10: 4940 | L10: 5779 | M10: 6472 | N10: 6564 | O10: 6738 | P10: 6323 | Q10: 5890
A11: -381526 | B11: -77037 | C11: Manaúra | D11: PB | E11: 6157 | F11: 6109 | G11: 6139 | H11: 5720 | I11: 5048 | J11: 4690 | K11: 4940 | L11: 5779 | M11: 6472 | N11: 6564 | O11: 6738 | P11: 6323 | Q11: 5890
A12: -37994 | B12: -77366 | C12: Princesa Isabel | D12: PB | E12: 6182 | F12: 6137 | G12: 6126 | H12: 5768 | I12: 5054 | J12: 4626 | K12: 4890 | L12: 5727 | M12: 6445 | N12: 6554 | O12: 6687 | P12: 6350 | Q12: 5879
A13: -370836 | B13: -7695 | C13: Prata | D13: PB | E13: 6183 | F13: 6100 | G13: 6063 | H13: 5734 | I13: 4948 | J13: 4454 | K13: 4611 | L13: 5383 | M13: 6232 | N13: 6475 | O13: 6657 | P13: 6353 | Q13: 5766
A14: -368828 | B14: -76725 | C14: Sumé | D14: PB | E14: 6118 | F14: 6053 | G14: 6032 | H14: 5636 | I14: 4885 | J14: 4401 | K14: 4573 | L14: 5282 | M14: 6138 | N14: 6378 | O14: 6574 | P14: 6277 | Q14: 5695
... A29: -355531 | B29: -76435 | C29: Natuba | D29: PB | E29: 5709 | F29: 5925 | G29: 5900 | H29: 5300 | I29: 4543 | J29: 4079 | K29: 4234 | L29: 5009 | M29: 5618 | N29: 5917 | O29: 6219 | P29: 6062 | Q29: 5376
A30: -384062 | B30: -7.48 | C30: Ibiara | D30: PB | E30: 6247 | F30: 6143 | G30: 6043 | H30: 5756 | I30: 5134 | J30: 4738 | K30: 5001 | L30: 5824 | M30: 6548 | N30: 6588 | O30: 6798 | P30: 6476 | Q30: 5941
A31: -38199 | B31: -75394 | C31: Curral Velho | D31: PB | E31: 6223 | F31: 6133 | G31: 6223 | H31: 5864 | I31: 5199 | J31: 4766 | K31: 5005 | L31: 5870 | M31: 6554 | N31: 6639 | O31: 6798 | P31: 6423 | Q31: 5974
A32: -380399 | B32: -74784 | C32: Nova Olinda | D32: PB | E32: 6252 | F32: 6179 | G32: 6251 | H32: 5888 | I32: 5179 | J32: 4757 | K32: 5001 | L32: 5862 | M32: 6534 | N32: 6608 | O32: 6782 | P32: 6428 | Q32: 5977
A33: -378202 | B33: -75383 | C33: Juru | D33: PB | E33: 6068 | F33: 6073 | G33: 6036 | H33: 5780 | I33: 5124 | J33: 4781 | K33: 5022 | L33: 5824 | M33: 6535 | N33: 6577 | O33: 6694 | P33: 6270 | Q33: 5899
A34: -37636 | B34: -75119 | C34: Ãgua Branca | D34: PB | E34: 6136 | F34: 6077 | G34: 6081 | H34: 5805 | I34: 5096 | J34: 4763 | K34: 5014 | L34: 5808 | M34: 6494 | N34: 6557 | O34: 6679 | P34: 6281 | Q34: 5899
A35: -366663 | B35: -74808 | C35: Serra Branca | D35: PB | E35: 5958 | F35: 5938 | G35: 5982 | H35: 5532 | I35: 4872 | J35: 4344 | K35: 4600 | L35: 5268 | M35: 6009 | N35: 6239 | O35: 6398 | P35: 6134 | Q35: 5606
A36: -362881 | B36: -74919 | C36: Cabaceiras | D36: PB | E36: 5922 | F36: 6058 | G36: 6017 | H36: 5501 | I36: 4827 | J36: 4236 | K36: 4475 | L36: 5143 | M36: 5864 | N36: 6132 | O36: 6366 | P36: 6192 | Q36: 5561
A37: -361323 | B37: -74826 | C37: Boqueirão | D37: PB | E37: 5877 | F37: 5884 | G37: 5869 | H37: 5388 | I37: 4733 | J37: 4183 | K37: 4374 | L37: 5019 | M37: 5702 | N37: 5957 | O37: 6231 | P37: 6062 | Q37: 5440
A38: -359958 | B38: -75178 | C38: Barra de Santana | D38: PB | E38: 5796 | F38: 5759 | G38: 5790 | H38: 5270 | I38: 4617 | J38: 4047 | K38: 4261 | L38: 4956 | M38: 5585 | N38: 5869 | O38: 6158 | P38: 5905 | Q38: 5334
A39: -357068 | B39: -75452 | C39: Aroeiras | D39: PB | E39: 5718 | F39: 5740 | G39: 5791 | H39: 5254 | I39: 4549 | J39: 4045 | K39: 4245 | L39: 4957 | M39: 5545 | N39: 5827 | O39: 6059 | P39: 5911 | Q39: 5303
A40: -349058 | B40: -75139 | C40: Caaporã | D40: PB | E40: 5746 | F40: 6018 | G40: 6004 | H40: 5306 | I40: 4648 | J40: 4264 | K40: 4333 | L40: 5109 | M40: 5549 | N40: 5871 | O40: 6031 | P40: 6045 | Q40: 5410
A41: -348154 | B41: -74668 | C41: Pitimbu | D41: PB | E41: 5810 | F41: 6081 | G41: 6054 | H41: 5352 | I41: 4782 | J41: 4366 | K41: 4423 | L41: 5242 | M41: 5668 | N41: 6037 | O41: 6073 | P41: 6164 | Q41: 5504
A42: -382181 | B42: -74206 | C42: Boa Ventura | D42: PB | E42: 6207 | F42: 6182 | G42: 6215 | H42: 5885 | I42: 5207 | J42: 4792 | K42: 5057 | L42: 5862 | M42: 6541 | N42: 6600 | O42: 6802 | P42: 6492 | Q42: 5987
... A49: -365321 | B49: -73861 | C49: São João do Cariri | D49: PB | E49: 5973 | F49: 5926 | G49: 6017 | H49: 5489 | I49: 4868 | J49: 4325 | K49: 4575 | L49: 5250 | M49: 5985 | N49: 6233 | O49: 6424 | P49: 6183 | Q49: 5604
A50: -360209 | B50: -7.42 | C50: Caturité | D50: PB | E50: 5859 | F50: 5812 | G50: 5850 | H50: 5339 | I50: 4690 | J50: 4165 | K50: 4374 | L50: 5036 | M50: 5681 | N50: 5973 | O50: 6217 | P50: 6003 | Q50: 5417
A51: -359036 | B51: -7367 | C51: Queimadas | D51: PB | E51: 5827 | F51: 5815 | G51: 5846 | H51: 5332 | I51: 4665 | J51: 4095 | K51: 4308 | L51: 4994 | M51: 5603 | N51: 5917 | O51: 6203 | P51: 5978 | Q51: 5382
A52: -357852 | B52: -73582 | C52: Fagundes | D52: PB | E52: 5703 | F52: 5746 | G52: 5807 | H52: 5249 | I52: 4549 | J52: 4068 | K52: 4184 | L52: 4888 | M52: 5422 | N52: 5731 | O52: 5994 | P52: 5901 | Q52: 5270
A53: -356277 | B53: -73784 | C53: Itatuba | D53: PB | E53: 5614 | F53: 5750 | G53: 5810 | H53: 5248 | I53: 4576 | J53: 4099 | K53: 4219 | L53: 4908 | M53: 5437 | N53: 5732 | O53: 6061 | P53: 5866 | Q53: 5277
A54: -354363 | B54: -73576 | C54: Salgado de São Félix | D54: PB | E54: 5695 | F54: 5874 | G54: 5896 | H54: 5282 | I54: 4598 | J54: 4164 | K54: 4278 | L54: 5101 | M54: 5588 | N54: 5811 | O54: 6117 | P54: 5941 | Q54: 5362
A55: -352387 | B55: -73587 | C55: Juripiranga | D55: PB | E55: 5697 | F55: 5882 | G55: 5872 | H55: 5327 | I55: 4635 | J55: 4244 | K55: 4374 | L55: 5091 | M55: 5602 | N55: 5818 | O55: 6102 | P55: 5973 | Q55: 5385
A56: -351125 | B56: -74025 | C56: Pedras de Fogo | D56: PB | E56: 5740 | F56: 5940 | G56: 5925 | H56: 5335 | I56: 4628 | J56: 4243 | K56: 4356 | L56: 5058 | M56: 5592 | N56: 5849 | O56: 6132 | P56: 6035 | Q56: 5403
A57: -34906 | B57: -74302 | C57: Alhandra | D57: PB | E57: 5748 | F57: 5984 | G57: 6002 | H57: 5293 | I57: 4701 | J57: 4291 | K57: 4339 | L57: 5142 | M57: 5553 | N57: 5877 | O57: 6015 | P57: 6049 | Q57: 5416
A58: -385136 | B58: -73138 | C58: Bonito de Santa Fé | D58: PB | E58: 5990 | F58: 6032 | G58: 5998 | H58: 5637 | I58: 5088 | J58: 4895 | K58: 5182 | L58: 5941 | M58: 6625 | N58: 6670 | O58: 6799 | P58: 6402 | Q58: 5938
A59: -383002 | B59: -72519 | C59: São José de Caiana | D59: PB | E59: 6144 | F59: 6071 | G59: 6095 | H59: 5811 | I59: 5246 | J59: 4932 | K59: 5167 | L59: 5976 | M59: 6592 | N59: 6643 | O59: 6838 | P59: 6461 | Q59: 5998
A60: -381508 | B60: -73024 | C60: Itaporanga | D60: PB | E60: 6219 | F60: 6179 | G60: 6255 | H60: 5873 | I60: 5205 | J60: 4838 | K60: 5081 | L60: 5913 | M60: 6544 | N60: 6609 | O60: 6786 | P60: 6460 | Q60: 5997
A61: -374277 | B61: -72579 | C61: Mãe d'Água | D61: PB | E61: 6035 | F61: 6044 | G61: 6053 | H61: 5792 | I61: 5106 | J61: 4707 | K61: 5071 | L61: 5853 | M61: 6473 | N61: 6586 | O61: 6681 | P61: 6362 | Q61: 5897
A62: -373513 | B62: -72623 | C62: Maturéia | D62: PB | E62: 6074 | F62: 6011 | G62: 6040 | H62: 5710 | I62: 5057 | J62: 4693 | K62: 5057 | L62: 5800 | M62: 6459 | N62: 6556 | O62: 6696 | P62: 6243 | Q62: 5866
... A163: -362474 | B163: -67663 | C163: Sossêgo | D163: PB | E163: 5838 | F163: 5751 | G163: 5795 | H163: 5369 | I163: 4800 | J163: 4335 | K163: 4547 | L163: 5268 | M163: 5820 | N163: 6146 | O163: 6295 | P163: 5982 | Q163: 5496
A164: -358182 | B164: -6.78 | C164: Casserengue | D164: PB | E164: 5783 | F164: 5783 | G164: 5869 | H164: 5344 | I164: 4772 | J164: 4315 | K164: 4476 | L164: 5222 | M164: 5681 | N164: 5940 | O164: 6164 | P164: 5914 | Q164: 5439
A165: -357555 | B165: -68285 | C165: Arara | D165: PB | E165: 5757 | F165: 5801 | G165: 5899 | H165: 5337 | I165: 4779 | J165: 4290 | K165: 4476 | L165: 5243 | M165: 5688 | N165: 5880 | O165: 6143 | P165: 5887 | Q165: 5431
A166: -356587 | B166: -67605 | C166: Solânea | D166: PB | E166: 5669 | F166: 5790 | G166: 5802 | H166: 5290 | I166: 4698 | J166: 4194 | K166: 4325 | L166: 5118 | M166: 5598 | N166: 5838 | O166: 6043 | P166: 5855 | Q166: 5352
A167: -35619 | B167: -68024 | C167: Borborema | D167: PB | E167: 5669 | F167: 5790 | G167: 5802 | H167: 5290 | I167: 4698 | J167: 4194 | K167: 4325 | L167: 5118 | M167: 5598 | N167: 5838 | O167: 6043 | P167: 5855 | Q167: 5352
A168: -356281 | B168: -68156 | C168: Serraria | D168: PB | E168: 5669 | F168: 5790 | G168: 5802 | H168: 5290 | I168: 4698 | J168: 4194 | K168: 4325 | L168: 5118 | M168: 5598 | N168: 5838 | O168: 6043 | P168: 5855 | Q168: 5352
A169: -355292 | B169: -68425 | C169: PilÃµezinhos | D169: PB | E169: 5505 | F169: 5593 | G169: 5650 | H169: 5171 | I169: 4609 | J169: 4150 | K169: 4231 | L169: 4994 | M169: 5440 | N169: 5669 | O169: 5872 | P169: 5632 | Q169: 5210
A170: -354375 | B170: -67517 | C170: Sertãozinho | D170: PB | E170: 5543 | F170: 5596 | G170: 5688 | H170: 5216 | I170: 4636 | J170: 4192 | K170: 4279 | L170: 5027 | M170: 5484 | N170: 5758 | O170: 6000 | P170: 5743 | Q170: 5263
A171: -354911 | B171: -6.78 | C171: Pirpirituba | D171: PB | E171: 5543 | F171: 5596 | G171: 5688 | H171: 5216 | I171: 4636 | J171: 4192 | K171: 4279 | L171: 5027 | M171: 5484 | N171: 5758 | O171: 6000 | P171: 5743 | Q171: 5263
A172: -352463 | B172: -68289 | C172: Itapororoca | D172: PB | E172: 5778 | F172: 5816 | G172: 5949 | H172: 5332 | I172: 4687 | J172: 4250 | K172: 4336 | L172: 5107 | M172: 5571 | N172: 5902 | O172: 6219 | P172: 6070 | Q172: 5418
A173: -351216 | B173: -68341 | C173: Mamanguape | D173: PB | E173: 5822 | F173: 5854 | G173: 5991 | H173: 5341 | I173: 4688 | J173: 4244 | K173: 4321 | L173: 5115 | M173: 5586 | N173: 5906 | O173: 6223 | P173: 6089 | Q173: 5432
A174: -350089 | B174: -67658 | C174: Marcação | D174: PB | E174: 5860 | F174: 5965 | G174: 6069 | H174: 5368 | I174: 4758 | J174: 4291 | K174: 4341 | L174: 5185 | M174: 5612 | N174: 5937 | O174: 6205 | P174: 6078 | Q174: 5472
A175: -350779 | B175: -68042 | C175: Rio Tinto | D175: PB | E175: 5860 | F175: 5965 | G175: 6069 | H175: 5368 | I175: 4758 | J175: 4291 | K175: 4341 | L175: 5185 | M175: 5612 | N175: 5937 | O175: 6205 | P175: 6078 | Q175: 5472
A176: -38643 | B176: -6718 | C176: Santa Helena | D176: PB | E176: 6111 | F176: 6077 | G176: 6080 | H176: 5744 | I176: 5248 | J176: 5052 | K176: 5380 | L176: 6050 | M176: 6451 | N176: 6602 | O176: 6747 | P176: 6337 | Q176: 5990
A177: -384555 | B177: -67216 | C177: São João do Rio do Peixe | D177: PB | E177: 6182 | F177: 6087 | G177: 6069 | H177: 5795 | I177: 5233 | J177: 5009 | K177: 5315 | L177: 6045 | M177: 6430 | N177: 6631 | O177: 6756 | P177: 6362 | Q177: 5993
A178: -375687 | B178: -67385 | C178: Vista Serrana | D178: PB | E178: 6075 | F178: 6219 | G178: 6284 | H178: 5881 | I178: 5306 | J178: 4834 | K178: 5145 | L178: 5903 | M178: 6441 | N178: 6602 | O178: 6661 | P178: 6316 | Q178: 5972
A179: -364198 | B179: -66789 | C179: Nova Palmeira | D179: PB | E179: 5986 | F179: 5911 | G179: 5896 | H179: 5533 | I179: 4941 | J179: 4492 | K179: 4775 | L179: 5511 | M179: 6067 | N179: 6428 | O179: 6496 | P179: 6128 | Q179: 5680
A180: -360674 | B180: -67186 | C180: Barra de Santa Rosa | D180: PB | E180: 5719 | F180: 5766 | G180: 5830 | H180: 5350 | I180: 4787 | J180: 4337 | K180: 4463 | L180: 5175 | M180: 5717 | N180: 5994 | O180: 6171 | P180: 5915 | Q180: 5435
A181: -356309 | B181: -67444 | C181: Bananeiras | D181: PB | E181: 5685 | F181: 5831 | G181: 5889 | H181: 5346 | I181: 4816 | J181: 4375 | K181: 4473 | L181: 5238 | M181: 5722 | N181: 5893 | O181: 6128 | P181: 5884 | Q181: 5440
A182: -355172 | B182: -67435 | C182: Belém | D182: PB | E182: 5611 | F182: 5677 | G182: 5739 | H182: 5246 | I182: 4769 | J182: 4304 | K182: 4372 | L182: 5130 | M182: 5593 | N182: 5783 | O182: 5968 | P182: 5699 | Q182: 5324
A183: -354184 | B183: -66888 | C183: Duas Estradas | D183: PB | E183: 5678 | F183: 5685 | G183: 5739 | H183: 5265 | I183: 4740 | J183: 4283 | K183: 4358 | L183: 5139 | M183: 5599 | N183: 5867 | O183: 6023 | P183: 5784 | Q183: 5346
... A210: -374491 | B210: -64857 | C210: São Bento | D210: PB | E210: 6219 | F210: 6233 | G210: 6237 | H210: 5905 | I210: 5301 | J210: 4854 | K210: 5131 | L210: 5877 | M210: 6439 | N210: 6624 | O210: 6612 | P210: 6313 | Q210: 5979
A211: -36.35 | B211: -65089 | C211: Picuí | D211: PB | E211: 5964 | F211: 5905 | G211: 5902 | H211: 5533 | I211: 4962 | J211: 4588 | K211: 4837 | L211: 5560 | M211: 6093 | N211: 6330 | O211: 6388 | P211: 5987 | Q211: 5671
A212: -362049 | B212: -64567 | C212: Nova Floresta | D212: PB | E212: 5875 | F212: 5844 | G212: 5871 | H212: 5497 | I212: 4916 | J212: 4505 | K212: 4722 | L212: 5471 | M212: 6004 | N212: 6248 | O212: 6304 | P212: 5931 | Q212: 5599
A213: -361549 | B213: -64857 | C213: Cuité | D213: PB | E213: 5695 | F213: 5719 | G213: 5686 | H213: 5355 | I213: 4760 | J213: 4322 | K213: 4521 | L213: 5264 | M213: 5779 | N213: 6051 | O213: 6179 | P213: 5800 | Q213: 5428
A214: -357409 | B214: -65346 | C214: Araruna | D214: PB | E214: 5777 | F214: 5853 | G214: 5939 | H214: 5410 | I214: 4877 | J214: 4406 | K214: 4588 | L214: 5299 | M214: 5772 | N214: 5929 | O214: 6118 | P214: 5820 | Q214: 5482
A215: -356613 | B215: -65431 | C215: Riachão | D215: PB | E215: 5607 | F215: 5729 | G215: 5789 | H215: 5368 | I215: 4838 | J215: 4378 | K215: 4537 | L215: 5224 | M215: 5592 | N215: 5750 | O215: 5978 | P215: 5681 | Q215: 5373
A216: -35637 | B216: -6488 | C216: Tacima | D216: PB | E216: 5607 | F216: 5729 | G216: 5789 | H216: 5368 | I216: 4838 | J216: 4378 | K216: 4537 | L216: 5224 | M216: 5592 | N216: 5750 | O216: 5978 | P216: 5681 | Q216: 5373
A217: -384912 | B217: -63992 | C217: Poço Dantas | D217: PB | E217: 5920 | F217: 5838 | G217: 5864 | H217: 5507 | I217: 5130 | J217: 4937 | K217: 5303 | L217: 6072 | M217: 6480 | N217: 6570 | O217: 6660 | P217: 6118 | Q217: 5867
A218: -379237 | B218: -64422 | C218: Bom Sucesso | D218: PB | E218: 6144 | F218: 6105 | G218: 6139 | H218: 5828 | I218: 5325 | J218: 5040 | K218: 5326 | L218: 6042 | M218: 6481 | N218: 6623 | O218: 6726 | P218: 6288 | Q218: 6006
A219: -378256 | B219: -63711 | C219: Brejo dos Santos | D219: PB | E219: 6136 | F219: 6131 | G219: 6104 | H219: 5810 | I219: 5312 | J219: 4993 | K219: 5301 | L219: 6024 | M219: 6553 | N219: 6639 | O219: 6693 | P219: 6278 | Q219: 5998
A220: -376486 | B220: -64411 | C220: Riacho dos Cavalos | D220: PB | E220: 6130 | F220: 6185 | G220: 6173 | H220: 5878 | I220: 5326 | J220: 4904 | K220: 5260 | L220: 5961 | M220: 6504 | N220: 6613 | O220: 6622 | P220: 6266 | Q220: 5985
A221: -364529 | B221: -6398 | C221: Frei Martinho | D221: PB | E221: 5950 | F221: 5889 | G221: 5897 | H221: 5570 | I221: 4984 | J221: 4556 | K221: 4805 | L221: 5620 | M221: 6142 | N221: 6317 | O221: 6423 | P221: 5979 | Q221: 5678
A222: -377473 | B222: -6341 | C222: Catolé do Rocha | D222: PB | E222: 6043 | F222: 6089 | G222: 6066 | H222: 5735 | I222: 5299 | J222: 4931 | K222: 5294 | L222: 6029 | M222: 6541 | N222: 6596 | O222: 6573 | P222: 6198 | Q222: 5950
A223: -374946 | B223: -63423 | C223: Brejo do Cruz | D223: PB | E223: 6180 | F223: 6237 | G223: 6160 | H223: 5857 | I223: 5351 | J223: 4951 | K223: 5224 | L223: 5915 | M223: 6475 | N223: 6637 | O223: 6653 | P223: 6276 | Q223: 5993
... A225: -373549 | B225: -62122 | C225: São José do Brejo do Cruz | D225: PB | E225: 6100 | F225: 6126 | G225: 6028 | H225: 5852 | I225: 5307 | J225: 4887 | K225: 5218 | L225: 5951 | M225: 6484 | N225: 6593 | O225: 6601 | P225: 6193 | Q225: 5945

Sheet Mala Direta
A1: Potência do Sistema | B1: Qtd Módulos | C1: Pot Módulos | D1: Qtd Inversor | E1: Pot Inversor | F1: CAPEX | G1: TMA | H1: TIR | I1: VPL | J1: payback | K1: Consumo | L1: Capex - extenso
A2: =Dados!$N$1 -> 5.85 | B2: =Dados!$J$1 -> 13 | C2: =Dados!$G$1 -> 450 | D2: =Dados!$B$2 -> 1 | E2: =Dados!$B$1 -> 5 | F2: =Dados!$B$15 -> 29058.826 | G2: 0.2 | H2: =IRR(Dados!N15:O40) -> 0.25669251 | I2: =NPV($G$2,Dados!$N$16:$O$40)+Dados!N15 -> 9693.8077 | J2: =Dados!$S$19 -> 4.3203908 | K2: =Dados!$P$5 -> 700
